MANIFEST.in
README.txt
setup.cfg
setup.py
Adjector.egg-info/PKG-INFO
Adjector.egg-info/SOURCES.txt
Adjector.egg-info/dependency_links.txt
Adjector.egg-info/entry_points.txt
Adjector.egg-info/namespace_packages.txt
Adjector.egg-info/paster_plugins.txt
Adjector.egg-info/requires.txt
Adjector.egg-info/top_level.txt
adjector/__init__.py
adjector/websetup.py
adjector/client/__init__.py
adjector/client/client.py
adjector/config/__init__.py
adjector/config/environment.py
adjector/config/middleware.py
adjector/config/routing.py
adjector/controllers/__init__.py
adjector/controllers/cj.py
adjector/controllers/creative.py
adjector/controllers/error.py
adjector/controllers/location.py
adjector/controllers/main.py
adjector/controllers/set.py
adjector/controllers/stats.py
adjector/controllers/track.py
adjector/controllers/zone.py
adjector/core/__init__.py
adjector/core/cj_util.py
adjector/core/conf.py
adjector/core/render.py
adjector/core/tracking.py
adjector/core/contrib/__init__.py
adjector/core/contrib/converters.py
adjector/forms/__init__.py
adjector/forms/forms.py
adjector/forms/validators.py
adjector/lib/__init__.py
adjector/lib/app_globals.py
adjector/lib/base.py
adjector/lib/cj_interface.py
adjector/lib/helpers.py
adjector/lib/middleware.py
adjector/lib/precache.py
adjector/lib/util.py
adjector/model/__init__.py
adjector/model/entities.py
adjector/model/meta.py
adjector/public/css/main.css
adjector/public/image/adjector_logo.png
adjector/public/js/adsense_tracker.js
adjector/templates/__init__.py
adjector/templates/cj/__init__.py
adjector/templates/cj/links.html
adjector/templates/common/__init__.py
adjector/templates/common/form.html
adjector/templates/common/master.html
adjector/templates/form/__init__.py
adjector/templates/form/basic.html
adjector/templates/form/widgets/__init__.py
adjector/templates/form/widgets/display_field.html
adjector/templates/form/widgets/generic_field.html
adjector/templates/list/__init__.py
adjector/templates/list/creatives.html
adjector/templates/list/locations.html
adjector/templates/list/sets.html
adjector/templates/list/zones.html
adjector/templates/list/includes/__init__.py
adjector/templates/list/includes/creative.html
adjector/templates/list/includes/location.html
