Metadata-Version: 1.0
Name: Adjector
Version: 1.0b2
Summary: A lightweight, fast, flexible ad server.  Stays out of your way.
Home-page: http://projects.icapsid.net/adjector
Author: David Isaacson
Author-email: david@icapsid.net
License: GPL v2 or v3 (at your option)
Platform: UNKNOWN
